{
  "name": "<%= _.slugify(connectorName) %>",
  "repository": "octoblu/<%= _.slugify(connectorName) %>",
  "version": "1.0.0",
  "main": "connector.js",
  "scripts": {
    "preinstall": "node -e \"try{require('./skip-install.js')}catch(e){}\"",
    "start": "node command.js",
    "test": "exit 0"
  },
  "dependencies": {
    "meshblu": "^1.30.1",
    "debug": "^2.1.0"
  },
  "bundledDependencies": [
    "request",
    "tar",
    "fstream"
  ],
  "platformDependencies": {
    "darwin": [],
    "win32": [],
    "win64": [],
    "linux": []
  },
  "keywords": [
    "meshblu-connector",
    "gateblu"
  ]
}
